{"cameraMode":{"drawMode":0,"name":"Shaded","section":"Shading Mode"},"sceneLighting":true,"audioPlay":false,"sceneViewState":{"m_AlwaysRefresh":false,"showFog":true,"showSkybox":true,"showFlares":true,"showImageEffects":true,"showParticleSystems":true,"showVisualEffectGraphs":true,"m_FxEnabled":true},"in2DMode":false,"pivot":{"x":26.92575454711914,"y":11.12951374053955,"z":51.494266510009769},"rotation":{"x":0.385648638010025,"y":0.28744959831237795,"z":-0.12991654872894288,"w":0.8678135275840759},"size":11.435544967651368,"orthographic":false}